[{"facility_id": "CFA 556", "days": "MoWe", "start_time": 8.0, "end_time": 10.75}, {"facility_id": "CFA 556", "days": "TuTh", "start_time": 15.5, "end_time": 18.25}, {"facility_id": "CFA 304", "days": "TuTh", "start_time": 15.5, "end_time": 18.25}, {"facility_id": "CFA 308", "days": "MoWe", "start_time": 8.0, "end_time": 10.75}, {"facility_id": "CFA 304", "days": "MoWe", "start_time": 8.0, "end_time": 10.75}, {"facility_id": "CFA 304", "days": "TuTh", "start_time": 12.5, "end_time": 15.25}, {"facility_id": "CFA 305", "days": "TuTh", "start_time": 12.5, "end_time": 15.25}, {"facility_id": "CFA 305", "days": "TuTh", "start_time": 15.5, "end_time": 18.25}, {"facility_id": "CFA 308", "days": "TuTh", "start_time": 12.5, "end_time": 15.25}, {"facility_id": "CFA 557", "days": "TuTh", "start_time": 15.5, "end_time": 18.25}, {"facility_id": "CFA 355", "days": "TuTh", "start_time": 12.5, "end_time": 15.25}, {"facility_id": "CFA 355", "days": "TuTh", "start_time": 15.5, "end_time": 18.25}, {"facility_id": "CFA 304", "days": "TuTh", "start_time": 8.0, "end_time": 10.75}, {"facility_id": "FLR 346", "days": "TuTh", "start_time": 12.5, "end_time": 15.25}, {"facility_id": "CFA 308", "days": "TuTh", "start_time": 8.0, "end_time": 10.75}, {"facility_id": "CFA 303", "days": "MoWe", "start_time": 14.5, "end_time": 17.25}, {"facility_id": "CFA 303", "days": "MoWe", "start_time": 8.0, "end_time": 10.75}, {"facility_id": "FLR 532", "days": "TuTh", "start_time": 12.5, "end_time": 15.25}, {"facility_id": "FLR 532", "days": "MoWe", "start_time": 14.5, "end_time": 17.25}, {"facility_id": "FLR 404D", "days": "MoWe", "start_time": 18.5, "end_time": 21.25}, {"facility_id": "CFA 558", "days": "TuTh", "start_time": 12.5, "end_time": 15.25}, {"facility_id": "CFA 500", "days": "Mo", "start_time": 18.5, "end_time": 21.25}, {"facility_id": "CFA 500", "days": "Tu", "start_time": 9.0, "end_time": 10.75}, {"facility_id": "CFA 507", "days": "TuTh", "start_time": 15.5, "end_time": 18.25}, {"facility_id": "CFA 508", "days": "MoWe", "start_time": 14.5, "end_time": 17.25}, {"facility_id": "CFA 500", "days": "Th", "start_time": 15.5, "end_time": 18.25}, {"facility_id": "CFA 357", "days": "TuTh", "start_time": 12.5, "end_time": 15.25}, {"facility_id": "CFA 357", "days": "TuTh", "start_time": 15.5, "end_time": 18.25}, {"facility_id": "CFA 355", "days": "We", "start_time": 8.0, "end_time": 10.75}, {"facility_id": "CFA 355", "days": "We", "start_time": 14.5, "end_time": 17.25}, {"facility_id": "FLR 404D", "days": "TuTh", "start_time": 12.5, "end_time": 15.25}, {"facility_id": "FLR 404D", "days": "Fr", "start_time": 14.5, "end_time": 17.25}, {"facility_id": "CFA 554", "days": "MoWe", "start_time": 14.5, "end_time": 17.25}, {"facility_id": "FLR 405", "days": "TuTh", "start_time": 12.5, "end_time": 15.25}, {"facility_id": "FLR 405", "days": "TuTh", "start_time": 15.5, "end_time": 18.25}, {"facility_id": "CFA 357", "days": "We", "start_time": 8.0, "end_time": 10.75}, {"facility_id": "CFA 357", "days": "We", "start_time": 14.5, "end_time": 17.25}, {"facility_id": "FLR 409", "days": "We", "start_time": 8.0, "end_time": 10.75}, {"facility_id": "FLR 409", "days": "Mo", "start_time": 8.0, "end_time": 10.75}, {"facility_id": "FLR 532", "days": "Tu", "start_time": 9.5, "end_time": 12.25}, {"facility_id": "FLR 404L", "days": "MoWe", "start_time": 14.5, "end_time": 17.25}, {"facility_id": "FLR 410", "days": "We", "start_time": 18.5, "end_time": 21.25}, {"facility_id": "CFA 559", "days": "MoWe", "start_time": 14.5, "end_time": 17.25}, {"facility_id": "FLR 532", "days": "We", "start_time": 18.5, "end_time": 21.25}, {"facility_id": "FLR 404D", "days": "MoWe", "start_time": 14.5, "end_time": 17.25}, {"facility_id": "FLR 534", "days": "We", "start_time": 18.5, "end_time": 21.25}, {"facility_id": "CFA 310", "days": "Th", "start_time": 18.5, "end_time": 21.25}, {"facility_id": "CFA 310", "days": "Tu", "start_time": 18.5, "end_time": 21.25}, {"facility_id": "CFA 500", "days": "Th", "start_time": 15.5, "end_time": 18.25}, {"facility_id": "FLR 410", "days": "We", "start_time": 14.5, "end_time": 17.25}, {"facility_id": "FLR 411", "days": "We", "start_time": 8.0, "end_time": 10.75}, {"facility_id": "FLR 410", "days": "Mo", "start_time": 18.5, "end_time": 21.25}, {"facility_id": "FLR 411", "days": "Mo", "start_time": 18.5, "end_time": 21.25}, {"facility_id": "FLR 410", "days": "Tu", "start_time": 11.0, "end_time": 12.25}, {"facility_id": "FLR 411", "days": "Th", "start_time": 11.0, "end_time": 12.25}, {"facility_id": "FLR 410", "days": "Mo", "start_time": 12.333333333333334, "end_time": 14.0}, {"facility_id": "FLR 410", "days": "Mo", "start_time": 14.5, "end_time": 16.166666666666668}, {"facility_id": "FLR 409", "days": "Mo", "start_time": 14.5, "end_time": 17.25}, {"facility_id": "FLR 409", "days": "Mo", "start_time": 8.0, "end_time": 10.75}, {"facility_id": "FLR 346", "days": "TuTh", "start_time": 12.5, "end_time": 15.25}, {"facility_id": "CFA 308", "days": "TuTh", "start_time": 8.0, "end_time": 10.75}, {"facility_id": "FLR 404D", "days": "TuTh", "start_time": 12.5, "end_time": 15.25}, {"facility_id": "CDS 164", "days": "Mo", "start_time": 14.5, "end_time": 17.25}, {"facility_id": "FLR 410", "days": "Fr", "start_time": 11.25, "end_time": 14.0}, {"facility_id": "FLR 404D", "days": "Fr", "start_time": 14.5, "end_time": 17.25}, {"facility_id": "CFA 554", "days": "MoWe", "start_time": 14.5, "end_time": 17.25}, {"facility_id": "FLR 410", "days": "Tu", "start_time": 12.5, "end_time": 15.25}, {"facility_id": "FLR 350", "days": "TuTh", "start_time": 18.5, "end_time": 21.25}, {"facility_id": "FLR 416", "days": "TuTh", "start_time": 18.5, "end_time": 21.25}, {"facility_id": "FLR 350", "days": "Th", "start_time": 13.5, "end_time": 15.25}, {"facility_id": "FLR 416", "days": "Th", "start_time": 15.5, "end_time": 17.25}, {"facility_id": "FLR 404M", "days": "We", "start_time": 16.5, "end_time": 18.25}, {"facility_id": "CFA 500", "days": "Fr", "start_time": 10.166666666666666, "end_time": 11.916666666666666}, {"facility_id": "FLR 338", "days": "Mo", "start_time": 12.333333333333334, "end_time": 14.083333333333334}, {"facility_id": "FLR 338", "days": "Mo", "start_time": 18.5, "end_time": 20.75}, {"facility_id": "FLR 303", "days": "Mo", "start_time": 12.333333333333334, "end_time": 14.083333333333334}, {"facility_id": "FLR 338", "days": "Mo", "start_time": 18.5, "end_time": 20.75}, {"facility_id": "FLR 404D", "days": "Th", "start_time": 9.5, "end_time": 12.25}, {"facility_id": "FLR 416", "days": "Tu", "start_time": 12.5, "end_time": 15.25}, {"facility_id": "FLR 410", "days": "Th", "start_time": 12.5, "end_time": 15.25}, {"facility_id": "FLR 410", "days": "Tu", "start_time": 12.5, "end_time": 15.25}, {"facility_id": "FLR 409", "days": "Tu", "start_time": 12.5, "end_time": 15.25}, {"facility_id": "FLR 409", "days": "Th", "start_time": 12.5, "end_time": 15.25}, {"facility_id": "FRC L240", "days": "TuTh", "start_time": 11.0, "end_time": 12.25}, {"facility_id": "CFA 109", "days": "TuTh", "start_time": 11.0, "end_time": 12.25}, {"facility_id": "FLR 254", "days": "MoWe", "start_time": 10.166666666666666, "end_time": 11.916666666666666}, {"facility_id": "FRC L240", "days": "Th", "start_time": 19.0, "end_time": 22.0}, {"facility_id": "CFA 175", "days": "Th", "start_time": 9.0, "end_time": 10.75}, {"facility_id": "CFA 203", "days": "Fr", "start_time": 12.333333333333334, "end_time": 14.083333333333334}, {"facility_id": "CFA 460", "days": "Fr", "start_time": 10.166666666666666, "end_time": 11.916666666666666}, {"facility_id": "CFA 219", "days": "Tu", "start_time": 9.0, "end_time": 10.75}, {"facility_id": "CFA 216", "days": "Tu", "start_time": 9.0, "end_time": 10.75}, {"facility_id": "CFA 219", "days": "TuTh", "start_time": 12.5, "end_time": 13.75}, {"facility_id": "CFA 167", "days": "TuTh", "start_time": 14.0, "end_time": 15.25}, {"facility_id": "CFA 216", "days": "Tu", "start_time": 11.25, "end_time": 12.083333333333334}, {"facility_id": "CFA 167", "days": "TuTh", "start_time": 14.0, "end_time": 15.25}, {"facility_id": "CFA 219", "days": "Sa", "start_time": 9.0, "end_time": 17.0}, {"facility_id": "CFA 219", "days": "TuTh", "start_time": 12.5, "end_time": 13.75}, {"facility_id": "CFA 171", "days": "TuTh", "start_time": 14.0, "end_time": 15.25}, {"facility_id": "CFA 167", "days": "TuTh", "start_time": 14.0, "end_time": 15.25}, {"facility_id": "CFA 167", "days": "TuTh", "start_time": 14.0, "end_time": 15.25}, {"facility_id": "CFA 216", "days": "Tu", "start_time": 18.5, "end_time": 21.25}, {"facility_id": "CFA 219", "days": "Tu", "start_time": 18.5, "end_time": 21.25}, {"facility_id": "CFA 167", "days": "TuTh", "start_time": 14.0, "end_time": 15.25}, {"facility_id": "CFA 219", "days": "Th", "start_time": 18.5, "end_time": 21.25}, {"facility_id": "CFA 156", "days": "TuTh", "start_time": 15.5, "end_time": 16.75}, {"facility_id": "CFA 154", "days": "TuTh", "start_time": 12.5, "end_time": 13.75}, {"facility_id": "CFA 154", "days": "We", "start_time": 16.5, "end_time": 18.25}, {"facility_id": "FLR 152", "days": "TuTh", "start_time": 12.5, "end_time": 13.75}, {"facility_id": "FLR 209", "days": "TuTh", "start_time": 12.5, "end_time": 13.75}, {"facility_id": "CFA B36", "days": "MoWe", "start_time": 14.5, "end_time": 16.25}, {"facility_id": "CFA 410", "days": "TuTh", "start_time": 14.0, "end_time": 15.25}, {"facility_id": "CFA 219", "days": "TuTh", "start_time": 11.0, "end_time": 12.25}, {"facility_id": "CFA B36", "days": "Th", "start_time": 18.5, "end_time": 21.25}, {"facility_id": "CFA B36", "days": "TuTh", "start_time": 11.0, "end_time": 12.25}, {"facility_id": "FLR 207", "days": "Th", "start_time": 12.5, "end_time": 15.25}, {"facility_id": "FLR 263", "days": "TuTh", "start_time": 14.0, "end_time": 15.25}, {"facility_id": "CFA 254", "days": "TuTh", "start_time": 11.0, "end_time": 12.25}, {"facility_id": "FLR 263", "days": "SaSu", "start_time": 9.0, "end_time": 17.0}, {"facility_id": "FLR 263", "days": "SaSu", "start_time": 9.0, "end_time": 17.0}, {"facility_id": "CFA 154", "days": "Mo", "start_time": 14.5, "end_time": 17.25}, {"facility_id": "FLR 152", "days": "We", "start_time": 14.5, "end_time": 17.25}, {"facility_id": "CFA B38", "days": "Tu", "start_time": 13.5, "end_time": 15.25}, {"facility_id": "FLR 263", "days": "We", "start_time": 8.0, "end_time": 10.75}, {"facility_id": "FLR 263", "days": "We", "start_time": 14.5, "end_time": 17.25}, {"facility_id": "FLR 209", "days": "We", "start_time": 14.5, "end_time": 17.25}, {"facility_id": "FLR 263", "days": "We", "start_time": 14.5, "end_time": 17.25}, {"facility_id": "FLR 209", "days": "We", "start_time": 14.5, "end_time": 17.25}, {"facility_id": "FLR 263", "days": "We", "start_time": 8.0, "end_time": 10.75}, {"facility_id": "CFA B37", "days": "MoWe", "start_time": 14.5, "end_time": 15.333333333333334}, {"facility_id": "CFA B37", "days": "MoWe", "start_time": 15.583333333333334, "end_time": 16.416666666666668}, {"facility_id": "CFA B37", "days": "MoWe", "start_time": 16.666666666666668, "end_time": 17.5}, {"facility_id": "CFA B37", "days": "TuTh", "start_time": 18.5, "end_time": 19.333333333333332}, {"facility_id": "CFA B37", "days": "MoWe", "start_time": 9.083333333333334, "end_time": 9.916666666666666}, {"facility_id": "CFA B37", "days": "TuTh", "start_time": 11.25, "end_time": 12.083333333333334}, {"facility_id": "CFA B37", "days": "MoWe", "start_time": 12.333333333333334, "end_time": 13.166666666666666}, {"facility_id": "CFA B37", "days": "TuTh", "start_time": 15.583333333333334, "end_time": 16.416666666666668}, {"facility_id": "CFA B37", "days": "MoWe", "start_time": 13.416666666666666, "end_time": 14.25}, {"facility_id": "CFA B37", "days": "MoWe", "start_time": 11.25, "end_time": 12.083333333333334}, {"facility_id": "CFA B37", "days": "MoWe", "start_time": 18.5, "end_time": 19.333333333333332}, {"facility_id": "CFA B37", "days": "MoWe", "start_time": 10.166666666666666, "end_time": 11.0}, {"facility_id": "CFA 414", "days": "MoWe", "start_time": 14.5, "end_time": 15.333333333333334}, {"facility_id": "CFA 414", "days": "MoWe", "start_time": 16.666666666666668, "end_time": 17.5}, {"facility_id": "CFA 414", "days": "MoWe", "start_time": 15.583333333333334, "end_time": 16.416666666666668}, {"facility_id": "CFA 219", "days": "TuTh", "start_time": 14.0, "end_time": 15.25}, {"facility_id": "CFA 156", "days": "Mo", "start_time": 12.333333333333334, "end_time": 14.083333333333334}, {"facility_id": "CFA 156", "days": "We", "start_time": 14.5, "end_time": 16.25}, {"facility_id": "CFA 156", "days": "We", "start_time": 12.333333333333334, "end_time": 14.083333333333334}, {"facility_id": "CFA 156", "days": "Fr", "start_time": 14.5, "end_time": 16.25}, {"facility_id": "CFA 216", "days": "Mo", "start_time": 16.666666666666668, "end_time": 17.5}, {"facility_id": "CFA 219", "days": "Mo", "start_time": 16.666666666666668, "end_time": 17.5}, {"facility_id": "CFA 216", "days": "TuTh", "start_time": 15.5, "end_time": 17.25}, {"facility_id": "CFA 165", "days": "MoWe", "start_time": 14.5, "end_time": 15.333333333333334}, {"facility_id": "CFA 165", "days": "MoWe", "start_time": 15.583333333333334, "end_time": 16.416666666666668}, {"facility_id": "CFA B22L", "days": "Th", "start_time": 11.0, "end_time": 12.25}, {"facility_id": "CFA 171", "days": "Fr", "start_time": 14.5, "end_time": 16.25}, {"facility_id": "CFA 171", "days": "Th", "start_time": 19.0, "end_time": 21.0}, {"facility_id": "FLR 236", "days": "TuTh", "start_time": 15.5, "end_time": 17.25}, {"facility_id": "CFA 414", "days": "Th", "start_time": 12.5, "end_time": 15.25}, {"facility_id": "CFA 414", "days": "Tu", "start_time": 13.5, "end_time": 15.25}, {"facility_id": "CFA 156", "days": "Mo", "start_time": 14.5, "end_time": 16.25}, {"facility_id": "CFA 167", "days": "Fr", "start_time": 8.0, "end_time": 9.25}, {"facility_id": "CFA 165", "days": "Fr", "start_time": 9.5, "end_time": 10.75}, {"facility_id": "CFA 167", "days": "Mo", "start_time": 16.5, "end_time": 18.25}, {"facility_id": "CFA 167", "days": "We", "start_time": 16.5, "end_time": 18.25}, {"facility_id": "CFA 165", "days": "Tu", "start_time": 15.5, "end_time": 17.25}, {"facility_id": "CFA 165", "days": "Tu", "start_time": 13.5, "end_time": 15.25}, {"facility_id": "CFA 167", "days": "We", "start_time": 14.5, "end_time": 16.25}, {"facility_id": "CFA 156", "days": "Tu", "start_time": 19.5, "end_time": 21.25}, {"facility_id": "CFA 171", "days": "Fr", "start_time": 8.0, "end_time": 9.75}, {"facility_id": "CFA 156", "days": "MoWe", "start_time": 16.666666666666668, "end_time": 17.5}, {"facility_id": "CFA B33F", "days": "We", "start_time": 18.5, "end_time": 21.25}, {"facility_id": "CFA 175", "days": "MoWeFr", "start_time": 11.25, "end_time": 14.0}, {"facility_id": "CFA 175", "days": "TuTh", "start_time": 15.5, "end_time": 18.25}, {"facility_id": "CFA B38", "days": "Th", "start_time": 13.5, "end_time": 15.25}, {"facility_id": "CFA 175", "days": "We", "start_time": 14.5, "end_time": 16.25}, {"facility_id": "CFA 175", "days": "We", "start_time": 14.5, "end_time": 16.25}, {"facility_id": "CFA 414", "days": "Tu", "start_time": 9.0, "end_time": 10.75}, {"facility_id": "CFA 156", "days": "MoWe", "start_time": 9.083333333333334, "end_time": 9.916666666666666}, {"facility_id": "CFA 167", "days": "We", "start_time": 19.0, "end_time": 22.0}, {"facility_id": "CFA 171", "days": "Tu", "start_time": 18.5, "end_time": 21.25}, {"facility_id": "CFA 167", "days": "Th", "start_time": 11.25, "end_time": 12.083333333333334}, {"facility_id": "CFA 106", "days": "Tu", "start_time": 14.0, "end_time": 15.25}, {"facility_id": "CFA 175", "days": "MoWeFr", "start_time": 11.25, "end_time": 14.0}, {"facility_id": "CFA 167", "days": "Mo", "start_time": 18.5, "end_time": 21.25}, {"facility_id": "CFA 171", "days": "Mo", "start_time": 18.5, "end_time": 21.25}, {"facility_id": "CFA 175", "days": "TuTh", "start_time": 15.5, "end_time": 18.25}, {"facility_id": "BAB 140", "days": "MoWe", "start_time": 18.5, "end_time": 20.5}, {"facility_id": "CFA 175", "days": "We", "start_time": 19.0, "end_time": 22.0}, {"facility_id": "CFA 171", "days": "MoFr", "start_time": 12.333333333333334, "end_time": 14.083333333333334}, {"facility_id": "FLR 237", "days": "Fr", "start_time": 14.5, "end_time": 17.25}, {"facility_id": "CFA 171", "days": "Th", "start_time": 19.0, "end_time": 21.0}, {"facility_id": "CFA 175", "days": "Fr", "start_time": 14.5, "end_time": 17.25}, {"facility_id": "CFA 414", "days": "Th", "start_time": 12.5, "end_time": 15.25}, {"facility_id": "CFA 414", "days": "Tu", "start_time": 13.5, "end_time": 15.25}, {"facility_id": "CFA 254", "days": "Fr", "start_time": 11.25, "end_time": 12.083333333333334}, {"facility_id": "CFA 254", "days": "Fr", "start_time": 12.333333333333334, "end_time": 13.166666666666666}, {"facility_id": "CFA 254", "days": "Th", "start_time": 13.5, "end_time": 15.25}, {"facility_id": "CFA 254", "days": "Th", "start_time": 13.5, "end_time": 15.25}, {"facility_id": "CFA 254", "days": "Th", "start_time": 13.5, "end_time": 15.25}, {"facility_id": "CFA 254", "days": "Mo", "start_time": 16.5, "end_time": 18.25}, {"facility_id": "CFA 167", "days": "Fr", "start_time": 8.0, "end_time": 9.25}, {"facility_id": "CFA 167", "days": "Fr", "start_time": 9.5, "end_time": 10.75}, {"facility_id": "CFA 165", "days": "Fr", "start_time": 9.5, "end_time": 10.75}, {"facility_id": "CFA 167", "days": "Mo", "start_time": 16.5, "end_time": 18.25}, {"facility_id": "CFA 167", "days": "We", "start_time": 16.5, "end_time": 18.25}, {"facility_id": "CFA 165", "days": "Tu", "start_time": 15.5, "end_time": 17.25}, {"facility_id": "CFA 165", "days": "Tu", "start_time": 13.5, "end_time": 15.25}, {"facility_id": "CFA 167", "days": "We", "start_time": 14.5, "end_time": 16.25}, {"facility_id": "CFA 156", "days": "Tu", "start_time": 19.5, "end_time": 21.25}, {"facility_id": "CFA 406", "days": "Mo", "start_time": 14.5, "end_time": 16.25}, {"facility_id": "CFA 171", "days": "Fr", "start_time": 8.0, "end_time": 9.75}, {"facility_id": "CFA B33F", "days": "We", "start_time": 18.5, "end_time": 21.25}, {"facility_id": "CFA B22L", "days": "Th", "start_time": 11.0, "end_time": 12.25}, {"facility_id": "CFA 219", "days": "Tu", "start_time": 17.0, "end_time": 18.25}, {"facility_id": "CFA 171", "days": "MoFr", "start_time": 10.166666666666666, "end_time": 11.916666666666666}, {"facility_id": "CFA 171", "days": "MoFr", "start_time": 10.166666666666666, "end_time": 11.916666666666666}, {"facility_id": "CFA 254", "days": "We", "start_time": 14.5, "end_time": 16.25}, {"facility_id": "CFA B38", "days": "Tu", "start_time": 8.0, "end_time": 8.833333333333334}, {"facility_id": "CFA B38", "days": "Th", "start_time": 8.0, "end_time": 8.833333333333334}, {"facility_id": "CFA B38", "days": "Fr", "start_time": 10.166666666666666, "end_time": 11.0}, {"facility_id": "CFA 410", "days": "Th", "start_time": 9.5, "end_time": 10.75}, {"facility_id": "FLR 236", "days": "We", "start_time": 12.5, "end_time": 14.083333333333334}, {"facility_id": "FLR 236", "days": "We", "start_time": 14.5, "end_time": 16.0}, {"facility_id": "CFA 254", "days": "WeFr", "start_time": 10.166666666666666, "end_time": 11.0}, {"facility_id": "CFA 254", "days": "WeFr", "start_time": 10.166666666666666, "end_time": 11.0}, {"facility_id": "FLR 236", "days": "Fr", "start_time": 13.0, "end_time": 14.5}, {"facility_id": "FLR 237", "days": "TuTh", "start_time": 14.0, "end_time": 15.25}, {"facility_id": "CFA 410", "days": "Mo", "start_time": 14.5, "end_time": 17.25}, {"facility_id": "CFA 216", "days": "MoWeFr", "start_time": 9.083333333333334, "end_time": 9.916666666666666}, {"facility_id": "CFA 219", "days": "MoWeFr", "start_time": 10.166666666666666, "end_time": 11.0}, {"facility_id": "CFA 216", "days": "MoWeFr", "start_time": 11.25, "end_time": 12.083333333333334}, {"facility_id": "CFA 414", "days": "MoWeFr", "start_time": 10.166666666666666, "end_time": 11.0}, {"facility_id": "CFA 414", "days": "MoWeFr", "start_time": 11.25, "end_time": 12.083333333333334}, {"facility_id": "CFA B36", "days": "MoWeFr", "start_time": 8.0, "end_time": 8.833333333333334}, {"facility_id": "CFA 154", "days": "MoWeTh", "start_time": 8.0, "end_time": 8.833333333333334}, {"facility_id": "CFA 165", "days": "TuThFr", "start_time": 8.0, "end_time": 8.833333333333334}, {"facility_id": "CFA 414", "days": "WeFr", "start_time": 8.0, "end_time": 8.833333333333334}, {"facility_id": "CFA 410", "days": "MoWeFr", "start_time": 8.0, "end_time": 8.833333333333334}, {"facility_id": "CFA 414", "days": "MoTuTh", "start_time": 8.0, "end_time": 8.833333333333334}, {"facility_id": "CFA 219", "days": "MoWeFr", "start_time": 9.083333333333334, "end_time": 9.916666666666666}, {"facility_id": "CFA 154", "days": "MoWeFr", "start_time": 10.166666666666666, "end_time": 11.0}, {"facility_id": "CFA 156", "days": "MoWeFr", "start_time": 10.166666666666666, "end_time": 11.0}, {"facility_id": "CFA 216", "days": "MoWeFr", "start_time": 8.0, "end_time": 8.833333333333334}, {"facility_id": "CFA 156", "days": "MoWeTh", "start_time": 8.0, "end_time": 8.833333333333334}, {"facility_id": "CFA 156", "days": "Fr", "start_time": 8.0, "end_time": 8.833333333333334}, {"facility_id": "CFA 219", "days": "Fr", "start_time": 8.0, "end_time": 8.833333333333334}, {"facility_id": "CFA 216", "days": "Th", "start_time": 8.0, "end_time": 8.833333333333334}, {"facility_id": "CFA 410", "days": "MoWe", "start_time": 10.166666666666666, "end_time": 11.0}, {"facility_id": "CFA 410", "days": "MoWe", "start_time": 11.25, "end_time": 12.083333333333334}, {"facility_id": "CFA 219", "days": "MoWe", "start_time": 14.5, "end_time": 15.333333333333334}, {"facility_id": "CFA 154", "days": "MoWe", "start_time": 11.25, "end_time": 12.083333333333334}, {"facility_id": "CFA 414", "days": "MoWe", "start_time": 9.083333333333334, "end_time": 9.916666666666666}, {"facility_id": "CFA 165", "days": "TuTh", "start_time": 11.25, "end_time": 12.083333333333334}, {"facility_id": "CFA 154", "days": "MoWeFr", "start_time": 12.333333333333334, "end_time": 13.166666666666666}, {"facility_id": "CFA 410", "days": "We", "start_time": 14.5, "end_time": 16.25}, {"facility_id": "CFA B38", "days": "Mo", "start_time": 16.5, "end_time": 18.25}, {"facility_id": "CFA 216", "days": "TuTh", "start_time": 14.0, "end_time": 15.25}, {"facility_id": "CFA 156", "days": "Tu", "start_time": 9.5, "end_time": 10.75}, {"facility_id": "CFA 156", "days": "TuTh", "start_time": 12.5, "end_time": 13.75}, {"facility_id": "CFA 410", "days": "TuTh", "start_time": 11.0, "end_time": 12.25}, {"facility_id": "CFA 410", "days": "TuTh", "start_time": 12.5, "end_time": 13.75}, {"facility_id": "CFA 414", "days": "MoWe", "start_time": 18.5, "end_time": 19.75}, {"facility_id": "CFA 410", "days": "We", "start_time": 14.5, "end_time": 16.25}, {"facility_id": "CFA B38", "days": "We", "start_time": 16.5, "end_time": 18.25}, {"facility_id": "CFA 219", "days": "MoWe", "start_time": 14.5, "end_time": 15.333333333333334}, {"facility_id": "CFA 154", "days": "Tu", "start_time": 15.5, "end_time": 17.25}, {"facility_id": "CFA 216", "days": "TuTh", "start_time": 12.5, "end_time": 13.75}, {"facility_id": "CFA B38", "days": "Tu", "start_time": 13.5, "end_time": 15.25}, {"facility_id": "CFA 410", "days": "MoWeFr", "start_time": 9.083333333333334, "end_time": 9.916666666666666}, {"facility_id": "CFA 156", "days": "TuTh", "start_time": 11.0, "end_time": 12.25}, {"facility_id": "CFA 154", "days": "MoWeFr", "start_time": 12.333333333333334, "end_time": 13.166666666666666}, {"facility_id": "CFA 216", "days": "MoWe", "start_time": 14.5, "end_time": 15.75}, {"facility_id": "BAB 140", "days": "TuTh", "start_time": 18.5, "end_time": 21.0}, {"facility_id": "BAB 140", "days": "MoWe", "start_time": 18.5, "end_time": 20.5}, {"facility_id": "BAB 148", "days": "MoWe", "start_time": 18.5, "end_time": 20.0}, {"facility_id": "BAB 148", "days": "Mo", "start_time": 20.25, "end_time": 21.75}, {"facility_id": "BAB 148", "days": "Fr", "start_time": 18.5, "end_time": 20.25}, {"facility_id": "BAB 148", "days": "Fr", "start_time": 16.5, "end_time": 18.25}, {"facility_id": "CFA 165", "days": "MoWe", "start_time": 18.5, "end_time": 20.0}, {"facility_id": "CFA 167", "days": "Th", "start_time": 18.5, "end_time": 20.5}, {"facility_id": "CFA 167", "days": "Mo", "start_time": 18.5, "end_time": 21.25}, {"facility_id": "CFA 171", "days": "Mo", "start_time": 18.5, "end_time": 21.25}, {"facility_id": "CFA 175", "days": "We", "start_time": 19.0, "end_time": 22.0}, {"facility_id": "BAB 140", "days": "TuTh", "start_time": 18.5, "end_time": 21.0}, {"facility_id": "BAB 140", "days": "TuTh", "start_time": 18.5, "end_time": 21.0}, {"facility_id": "BAB 140", "days": "MoWe", "start_time": 18.5, "end_time": 20.5}, {"facility_id": "BAB 148", "days": "MoWe", "start_time": 18.5, "end_time": 20.0}, {"facility_id": "BAB 148", "days": "Mo", "start_time": 20.25, "end_time": 21.75}, {"facility_id": "BAB 148", "days": "Fr", "start_time": 18.5, "end_time": 20.25}, {"facility_id": "BAB 148", "days": "Fr", "start_time": 16.5, "end_time": 18.25}, {"facility_id": "CFA 165", "days": "MoWe", "start_time": 18.5, "end_time": 20.0}, {"facility_id": "CFA 167", "days": "Th", "start_time": 18.5, "end_time": 20.5}, {"facility_id": "CFA 167", "days": "Mo", "start_time": 18.5, "end_time": 21.25}, {"facility_id": "CFA 171", "days": "Mo", "start_time": 18.5, "end_time": 21.25}, {"facility_id": "CFA 175", "days": "We", "start_time": 19.0, "end_time": 22.0}, {"facility_id": "CFA B33G", "days": "We", "start_time": 14.5, "end_time": 16.25}, {"facility_id": "CFA B33G", "days": "Mo", "start_time": 16.5, "end_time": 18.25}, {"facility_id": "CFA 154", "days": "Tu", "start_time": 11.0, "end_time": 12.25}, {"facility_id": "THA 101", "days": "Tu", "start_time": 15.5, "end_time": 16.75}, {"facility_id": "CGS 121", "days": "Tu", "start_time": 12.5, "end_time": 15.25}, {"facility_id": "CFA 500", "days": "Tu", "start_time": 12.5, "end_time": 15.25}, {"facility_id": "CFA 105", "days": "MoWe", "start_time": 14.5, "end_time": 16.25}, {"facility_id": "CFA 356", "days": "MoWe", "start_time": 10.166666666666666, "end_time": 11.916666666666666}, {"facility_id": "CFA 105", "days": "MoWe", "start_time": 12.333333333333334, "end_time": 14.083333333333334}, {"facility_id": "CFA 354", "days": "Fr", "start_time": 10.166666666666666, "end_time": 11.916666666666666}, {"facility_id": "CFA 354", "days": "Fr", "start_time": 12.333333333333334, "end_time": 14.083333333333334}, {"facility_id": "CFA 109", "days": "Tu", "start_time": 15.5, "end_time": 17.25}, {"facility_id": "CFA 109", "days": "We", "start_time": 10.166666666666666, "end_time": 11.916666666666666}, {"facility_id": "CFA 109", "days": "WeFr", "start_time": 14.5, "end_time": 16.25}, {"facility_id": "CFA 109", "days": "Th", "start_time": 15.5, "end_time": 17.25}, {"facility_id": "THA 422", "days": "MoWe", "start_time": 12.333333333333334, "end_time": 14.083333333333334}, {"facility_id": "CFA 454", "days": "Th", "start_time": 13.5, "end_time": 15.25}, {"facility_id": "CFA 354", "days": "Tu", "start_time": 9.0, "end_time": 10.75}, {"facility_id": "THA 422", "days": "We", "start_time": 10.166666666666666, "end_time": 11.916666666666666}, {"facility_id": "THA 422", "days": "Fr", "start_time": 10.166666666666666, "end_time": 11.916666666666666}, {"facility_id": "THA 415", "days": "Tu", "start_time": 8.0, "end_time": 10.75}, {"facility_id": "CFA 106", "days": "MoWe", "start_time": 10.166666666666666, "end_time": 11.916666666666666}, {"facility_id": "FLR 254", "days": "We", "start_time": 12.333333333333334, "end_time": 14.083333333333334}, {"facility_id": "CFA 106", "days": "Th", "start_time": 13.5, "end_time": 15.25}, {"facility_id": "CFA 354", "days": "MoWe", "start_time": 14.5, "end_time": 16.25}, {"facility_id": "CFA 354", "days": "Fr", "start_time": 14.5, "end_time": 16.25}, {"facility_id": "CFA 354", "days": "MoWe", "start_time": 10.166666666666666, "end_time": 11.916666666666666}, {"facility_id": "CFA 354", "days": "Th", "start_time": 15.5, "end_time": 16.75}, {"facility_id": "CFA 454", "days": "MoWe", "start_time": 14.5, "end_time": 16.25}, {"facility_id": "CFA 109", "days": "MoFr", "start_time": 8.0, "end_time": 9.75}, {"facility_id": "CFA 109", "days": "MoFr", "start_time": 10.166666666666666, "end_time": 11.916666666666666}, {"facility_id": "FLR 254", "days": "MoFr", "start_time": 14.5, "end_time": 16.25}, {"facility_id": "CFA 356", "days": "TuTh", "start_time": 14.0, "end_time": 15.25}, {"facility_id": "CFA 106", "days": "Th", "start_time": 9.5, "end_time": 10.75}, {"facility_id": "CFA 106", "days": "Tu", "start_time": 9.5, "end_time": 10.75}, {"facility_id": "CFA 352", "days": "Fr", "start_time": 9.5, "end_time": 10.75}, {"facility_id": "CFA 454", "days": "Mo", "start_time": 16.5, "end_time": 18.25}, {"facility_id": "CFA 454", "days": "MoFr", "start_time": 12.333333333333334, "end_time": 14.083333333333334}, {"facility_id": "CFA 352", "days": "WeFr", "start_time": 12.333333333333334, "end_time": 14.083333333333334}, {"facility_id": "CFA 354", "days": "Tu", "start_time": 15.5, "end_time": 16.75}, {"facility_id": "THA 307", "days": "Tu", "start_time": 12.5, "end_time": 15.25}, {"facility_id": "THA 415", "days": "Fr", "start_time": 14.5, "end_time": 17.25}, {"facility_id": "THA 422", "days": "We", "start_time": 14.5, "end_time": 17.25}, {"facility_id": "THA 201", "days": "Fr", "start_time": 11.25, "end_time": 14.0}, {"facility_id": "THA 307", "days": "Th", "start_time": 13.5, "end_time": 15.25}, {"facility_id": "CFA 460", "days": "Mo", "start_time": 10.166666666666666, "end_time": 11.916666666666666}, {"facility_id": "CFA 454", "days": "MoWe", "start_time": 10.166666666666666, "end_time": 11.916666666666666}, {"facility_id": "THA 125", "days": "Mo", "start_time": 14.5, "end_time": 16.25}, {"facility_id": "THA 123", "days": "We", "start_time": 10.166666666666666, "end_time": 11.916666666666666}, {"facility_id": "CFA 105", "days": "Fr", "start_time": 10.166666666666666, "end_time": 11.916666666666666}, {"facility_id": "CFA 105", "days": "Fr", "start_time": 14.5, "end_time": 16.25}, {"facility_id": "CFA 106", "days": "WeFr", "start_time": 12.333333333333334, "end_time": 14.083333333333334}, {"facility_id": "CFA 106", "days": "Fr", "start_time": 10.166666666666666, "end_time": 11.916666666666666}, {"facility_id": "THA 307", "days": "Mo", "start_time": 10.166666666666666, "end_time": 11.916666666666666}, {"facility_id": "CFA 352", "days": "Th", "start_time": 9.0, "end_time": 10.75}, {"facility_id": "CFA 352", "days": "MoWe", "start_time": 10.166666666666666, "end_time": 11.916666666666666}, {"facility_id": "CFA 106", "days": "Mo", "start_time": 18.5, "end_time": 20.25}, {"facility_id": "CFA 352", "days": "MoWeFr", "start_time": 14.5, "end_time": 16.25}, {"facility_id": "CFA 109", "days": "TuTh", "start_time": 13.5, "end_time": 15.25}, {"facility_id": "CFA 109", "days": "TuTh", "start_time": 9.0, "end_time": 10.75}, {"facility_id": "FLR 346", "days": "Fr", "start_time": 10.166666666666666, "end_time": 11.916666666666666}, {"facility_id": "THA 412", "days": "Mo", "start_time": 14.5, "end_time": 17.25}, {"facility_id": "CFA 106", "days": "Th", "start_time": 11.0, "end_time": 12.25}, {"facility_id": "CFA 106", "days": "Tu", "start_time": 12.5, "end_time": 13.75}, {"facility_id": "THA 412", "days": "Tu", "start_time": 15.5, "end_time": 16.75}, {"facility_id": "THA 124", "days": "Tu", "start_time": 15.5, "end_time": 16.75}, {"facility_id": "THA 201", "days": "Tu", "start_time": 15.5, "end_time": 16.75}, {"facility_id": "THA 307", "days": "Tu", "start_time": 15.5, "end_time": 16.75}, {"facility_id": "THA 422", "days": "Tu", "start_time": 15.5, "end_time": 16.75}, {"facility_id": "THA 125", "days": "Tu", "start_time": 15.5, "end_time": 16.75}, {"facility_id": "THA 415", "days": "Tu", "start_time": 15.5, "end_time": 16.75}, {"facility_id": "CFA 460", "days": "Th", "start_time": 15.5, "end_time": 17.25}, {"facility_id": "THA 201", "days": "We", "start_time": 14.5, "end_time": 17.25}, {"facility_id": "CFA 352", "days": "Tu", "start_time": 15.5, "end_time": 16.75}, {"facility_id": "THA 124", "days": "Th", "start_time": 11.0, "end_time": 15.25}, {"facility_id": "THA 412", "days": "TuTh", "start_time": 17.0, "end_time": 18.25}, {"facility_id": "THA 124", "days": "TuTh", "start_time": 17.0, "end_time": 18.25}, {"facility_id": "THA 201", "days": "TuTh", "start_time": 17.0, "end_time": 18.25}, {"facility_id": "THA 307", "days": "TuTh", "start_time": 17.0, "end_time": 18.25}, {"facility_id": "THA 422", "days": "TuTh", "start_time": 17.0, "end_time": 18.25}, {"facility_id": "THA 125", "days": "TuTh", "start_time": 17.0, "end_time": 18.25}, {"facility_id": "THA 415", "days": "TuTh", "start_time": 17.0, "end_time": 18.25}, {"facility_id": "CFA 105", "days": "TuWeThFr", "start_time": 18.5, "end_time": 22.5}, {"facility_id": "CFA 106", "days": "TuWeThFr", "start_time": 18.5, "end_time": 22.5}, {"facility_id": "CFA 109", "days": "TuWeThFr", "start_time": 18.5, "end_time": 22.5}, {"facility_id": "CFA 352", "days": "TuWeThFr", "start_time": 18.5, "end_time": 22.5}, {"facility_id": "CFA 354", "days": "TuWeThFr", "start_time": 18.5, "end_time": 22.5}, {"facility_id": "CFA 356", "days": "TuWeThFr", "start_time": 18.5, "end_time": 22.5}, {"facility_id": "CFA 454", "days": "TuWeThFr", "start_time": 18.5, "end_time": 22.5}, {"facility_id": "CFA 460", "days": "TuWeThFr", "start_time": 18.5, "end_time": 22.5}, {"facility_id": "CFA 468", "days": "TuWeThFr", "start_time": 18.5, "end_time": 22.5}, {"facility_id": "CFA 104", "days": "TuWeThFr", "start_time": 18.5, "end_time": 22.5}, {"facility_id": "THA 412", "days": "Th", "start_time": 12.5, "end_time": 15.25}, {"facility_id": "THA 123", "days": "Mo", "start_time": 12.333333333333334, "end_time": 14.083333333333334}, {"facility_id": "THA 422", "days": "Mo", "start_time": 14.5, "end_time": 16.25}, {"facility_id": "THA 412", "days": "Tu", "start_time": 9.0, "end_time": 10.75}, {"facility_id": "THA 123", "days": "Mo", "start_time": 14.5, "end_time": 17.25}, {"facility_id": "THA 307", "days": "Th", "start_time": 9.0, "end_time": 10.75}, {"facility_id": "CFA 203", "days": "Mo", "start_time": 12.333333333333334, "end_time": 14.083333333333334}, {"facility_id": "THA 415", "days": "Mo", "start_time": 12.333333333333334, "end_time": 14.083333333333334}, {"facility_id": "CFA 460", "days": "Mo", "start_time": 14.5, "end_time": 17.25}, {"facility_id": "THA 412", "days": "We", "start_time": 14.5, "end_time": 17.25}, {"facility_id": "FLR 254", "days": "Th", "start_time": 13.5, "end_time": 15.25}, {"facility_id": "CFA 356", "days": "Fr", "start_time": 14.5, "end_time": 16.25}, {"facility_id": "CFA 352", "days": "TuTh", "start_time": 13.5, "end_time": 15.25}, {"facility_id": "CFA 460", "days": "We", "start_time": 10.166666666666666, "end_time": 11.916666666666666}, {"facility_id": "CFA 468", "days": "Mo", "start_time": 16.5, "end_time": 18.25}, {"facility_id": "CFA 468", "days": "Mo", "start_time": 12.333333333333334, "end_time": 14.083333333333334}, {"facility_id": "CFA 109", "days": "Mo", "start_time": 18.5, "end_time": 21.25}, {"facility_id": "CFA 109", "days": "Mo", "start_time": 14.5, "end_time": 16.25}, {"facility_id": "CFA 106", "days": "Tu", "start_time": 11.0, "end_time": 12.25}, {"facility_id": "CFA 105", "days": "TuWeThFr", "start_time": 18.5, "end_time": 22.5}, {"facility_id": "CFA 106", "days": "TuWeThFr", "start_time": 18.5, "end_time": 22.5}, {"facility_id": "CFA 109", "days": "TuWeThFr", "start_time": 18.5, "end_time": 22.5}, {"facility_id": "CFA 352", "days": "TuWeThFr", "start_time": 18.5, "end_time": 22.5}, {"facility_id": "CFA 354", "days": "TuWeThFr", "start_time": 18.5, "end_time": 22.5}, {"facility_id": "CFA 356", "days": "TuWeThFr", "start_time": 18.5, "end_time": 22.5}, {"facility_id": "CFA 454", "days": "TuWeThFr", "start_time": 18.5, "end_time": 22.5}, {"facility_id": "CFA 460", "days": "TuWeThFr", "start_time": 18.5, "end_time": 22.5}, {"facility_id": "CFA 468", "days": "TuWeThFr", "start_time": 18.5, "end_time": 22.5}, {"facility_id": "CFA 104", "days": "TuWeThFr", "start_time": 18.5, "end_time": 22.5}, {"facility_id": "THA 123", "days": "We", "start_time": 14.5, "end_time": 16.25}, {"facility_id": "THA 415", "days": "Mo", "start_time": 14.5, "end_time": 16.25}, {"facility_id": "THA 124", "days": "Th", "start_time": 11.0, "end_time": 15.25}, {"facility_id": "THA 412", "days": "We", "start_time": 10.166666666666666, "end_time": 11.916666666666666}, {"facility_id": "THA 412", "days": "Tu", "start_time": 9.0, "end_time": 10.75}, {"facility_id": "THA 201", "days": "Fr", "start_time": 14.5, "end_time": 17.25}, {"facility_id": "THA 307", "days": "Tu", "start_time": 9.0, "end_time": 10.75}, {"facility_id": "THA 307", "days": "MoFr", "start_time": 12.333333333333334, "end_time": 14.083333333333334}, {"facility_id": "THA 415", "days": "Fr", "start_time": 10.166666666666666, "end_time": 11.916666666666666}, {"facility_id": "CFA 356", "days": "WeFr", "start_time": 12.333333333333334, "end_time": 14.083333333333334}, {"facility_id": "THA 123", "days": "We", "start_time": 10.166666666666666, "end_time": 11.916666666666666}, {"facility_id": "THA 123", "days": "Mo", "start_time": 12.333333333333334, "end_time": 14.083333333333334}, {"facility_id": "THA 201", "days": "We", "start_time": 14.5, "end_time": 17.25}, {"facility_id": "FLR 254", "days": "Tu", "start_time": 12.5, "end_time": 15.25}, {"facility_id": "CFA 109", "days": "WeFr", "start_time": 12.333333333333334, "end_time": 14.083333333333334}, {"facility_id": "CFA 106", "days": "We", "start_time": 14.5, "end_time": 16.25}, {"facility_id": "FLR 254", "days": "We", "start_time": 14.5, "end_time": 16.25}, {"facility_id": "FLR 346", "days": "Fr", "start_time": 10.166666666666666, "end_time": 11.916666666666666}, {"facility_id": "THA 412", "days": "Tu", "start_time": 15.5, "end_time": 16.75}, {"facility_id": "THA 124", "days": "Tu", "start_time": 15.5, "end_time": 16.75}, {"facility_id": "THA 201", "days": "Tu", "start_time": 15.5, "end_time": 16.75}, {"facility_id": "THA 307", "days": "Tu", "start_time": 15.5, "end_time": 16.75}, {"facility_id": "THA 422", "days": "Tu", "start_time": 15.5, "end_time": 16.75}, {"facility_id": "THA 125", "days": "Tu", "start_time": 15.5, "end_time": 16.75}, {"facility_id": "THA 415", "days": "Tu", "start_time": 15.5, "end_time": 16.75}, {"facility_id": "THA 412", "days": "TuTh", "start_time": 17.0, "end_time": 18.25}, {"facility_id": "THA 124", "days": "TuTh", "start_time": 17.0, "end_time": 18.25}, {"facility_id": "THA 201", "days": "TuTh", "start_time": 17.0, "end_time": 18.25}, {"facility_id": "THA 307", "days": "TuTh", "start_time": 17.0, "end_time": 18.25}, {"facility_id": "THA 422", "days": "TuTh", "start_time": 17.0, "end_time": 18.25}, {"facility_id": "THA 125", "days": "TuTh", "start_time": 17.0, "end_time": 18.25}, {"facility_id": "THA 415", "days": "TuTh", "start_time": 17.0, "end_time": 18.25}, {"facility_id": "FLR 254", "days": "TuTh", "start_time": 17.0, "end_time": 18.25}, {"facility_id": "THA 412", "days": "Th", "start_time": 12.5, "end_time": 15.25}, {"facility_id": "THA 412", "days": "Tu", "start_time": 15.5, "end_time": 16.75}, {"facility_id": "THA 124", "days": "Tu", "start_time": 15.5, "end_time": 16.75}, {"facility_id": "THA 201", "days": "Tu", "start_time": 15.5, "end_time": 16.75}, {"facility_id": "THA 307", "days": "Tu", "start_time": 15.5, "end_time": 16.75}, {"facility_id": "THA 422", "days": "Tu", "start_time": 15.5, "end_time": 16.75}, {"facility_id": "THA 125", "days": "Tu", "start_time": 15.5, "end_time": 16.75}, {"facility_id": "THA 415", "days": "Tu", "start_time": 15.5, "end_time": 16.75}, {"facility_id": "THA 125", "days": "Mo", "start_time": 14.5, "end_time": 16.25}, {"facility_id": "THA 422", "days": "Fr", "start_time": 14.5, "end_time": 17.25}, {"facility_id": "THA 422", "days": "Tu", "start_time": 13.5, "end_time": 15.25}, {"facility_id": "THA 123", "days": "We", "start_time": 8.0, "end_time": 9.75}, {"facility_id": "THA 124", "days": "Th", "start_time": 9.0, "end_time": 10.75}, {"facility_id": "THA 124", "days": "Th", "start_time": 11.0, "end_time": 15.25}, {"facility_id": "THA 208", "days": "Mo", "start_time": 12.333333333333334, "end_time": 14.083333333333334}, {"facility_id": "THA 412", "days": "Mo", "start_time": 14.5, "end_time": 17.25}, {"facility_id": "CFA 203", "days": "Mo", "start_time": 12.333333333333334, "end_time": 14.083333333333334}, {"facility_id": "THA 307", "days": "Mo", "start_time": 10.166666666666666, "end_time": 11.916666666666666}, {"facility_id": "CFA 460", "days": "Tu", "start_time": 9.0, "end_time": 10.75}, {"facility_id": "CFA 352", "days": "Mo", "start_time": 16.5, "end_time": 18.25}, {"facility_id": "THA 412", "days": "We", "start_time": 10.166666666666666, "end_time": 11.916666666666666}, {"facility_id": "THA 123", "days": "We", "start_time": 14.5, "end_time": 16.25}, {"facility_id": "THA 124", "days": "Th", "start_time": 11.0, "end_time": 15.25}, {"facility_id": "CFA 352", "days": "Mo", "start_time": 16.5, "end_time": 18.25}, {"facility_id": "THA 412", "days": "We", "start_time": 14.5, "end_time": 17.25}, {"facility_id": "THA 307", "days": "MoFr", "start_time": 12.333333333333334, "end_time": 14.083333333333334}, {"facility_id": "THA 412", "days": "Mo", "start_time": 12.333333333333334, "end_time": 14.083333333333334}, {"facility_id": "THA 412", "days": "Tu", "start_time": 13.5, "end_time": 15.25}, {"facility_id": "THA 307", "days": "Mo", "start_time": 14.5, "end_time": 17.25}, {"facility_id": "THA 201", "days": "Fr", "start_time": 11.25, "end_time": 14.0}, {"facility_id": "THA 201", "days": "Fr", "start_time": 14.5, "end_time": 17.25}, {"facility_id": "THA 307", "days": "Fr", "start_time": 14.5, "end_time": 16.25}, {"facility_id": "THA 415", "days": "Fr", "start_time": 10.166666666666666, "end_time": 11.916666666666666}, {"facility_id": "THA 412", "days": "Mo", "start_time": 18.5, "end_time": 21.25}, {"facility_id": "THA 415", "days": "We", "start_time": 14.5, "end_time": 17.25}, {"facility_id": "CFA 454", "days": "Fr", "start_time": 10.166666666666666, "end_time": 11.916666666666666}, {"facility_id": "THA 124", "days": "We", "start_time": 12.333333333333334, "end_time": 14.083333333333334}, {"facility_id": "THA 415", "days": "We", "start_time": 12.333333333333334, "end_time": 14.083333333333334}, {"facility_id": "THA 412", "days": "Tu", "start_time": 13.5, "end_time": 15.25}, {"facility_id": "CFA 454", "days": "Th", "start_time": 15.5, "end_time": 16.75}, {"facility_id": "THA 415", "days": "Th", "start_time": 9.0, "end_time": 10.75}, {"facility_id": "THA 415", "days": "We", "start_time": 9.083333333333334, "end_time": 11.916666666666666}, {"facility_id": "THA 415", "days": "Mo", "start_time": 16.5, "end_time": 18.25}, {"facility_id": "THA 412", "days": "Tu", "start_time": 13.5, "end_time": 15.25}]